pydantic_fabricated/__init__.py
pydantic_fabricated/_class_model_generator.py
pydantic_fabricated/_params_model_generator.py
pydantic_fabricated/_union_generator.py
pydantic_fabricated/metaclass.py
pydantic_fabricated/py.typed
pydantic_fabricated-1.0.1.dist-info/METADATA
pydantic_fabricated-1.0.1.dist-info/WHEEL
pydantic_fabricated-1.0.1.dist-info/licenses/LICENSE
pydantic_fabricated-1.0.1.dist-info/licenses/NOTICE
pydantic_fabricated-1.0.1.dist-info/RECORD
