Metadata-Version: 2.4
Name: pydantic-fabricated
Version: 1.0.1
Summary: Metaclass for fabricating subclasses from dictionaries inside Pydantic models.
Project-URL: homepage, https://github.com/KRunchPL/pydantic-fabricated
Project-URL: repository, https://github.com/KRunchPL/pydantic-fabricated
Project-URL: documentation, https://github.com/KRunchPL/pydantic-fabricated
Author-email: KRunchPL <krunchfrompoland@gmail.com>
License-Expression: Apache-2.0
License-File: LICENSE
License-File: NOTICE
Requires-Python: <4.0,>=3.13
Requires-Dist: pydantic<3.0.0,>=2.11.9
